[{"id":"254845","type":"good","language_code":"sl","title":"Vlado Dimovski","summary":"Vlado Dimovski, slovenski ekonomist, filozof, politik, svetovalec in univerzitetni profesor, * 21. julij 1960, Postojna.","url":"https://sl.wikipedia.org/wiki/Vlado_Dimovski","thumbnail_url":"https://upload.wikimedia.org/wikipedia/commons/thumb/7/7a/Vlado_Dimovski.jpg/150px-Vlado_Dimovski.jpg"},{"id":"436059","type":"good","language_code":"sl","title":"Papež Sergij IV.","summary":"Papež Sergij IV. ((latinsko Papa Sergius Quartus)  rojen kot Pietro Martino Buccaporci, je bil italijaski kardinal in papež, * okrog 970, Rim (Papeška država, Sveto rimsko cesarstvo), † 12. maj 1012, Rim (Papeška država, Sveto rimsko cesarstvo; danes: Italija) \nPapež je bil od julija 1009 do svoje smrti, 12. maja 1012.","url":"https://sl.wikipedia.org/wiki/Pape%C5%BE_Sergij_IV.","thumbnail_url":"https://upload.wikimedia.org/wikipedia/commons/thumb/5/52/Sergius_IV.jpg/150px-Sergius_IV.jpg"}]